{
  "id": "ai-analytics/recommendations",
  "title": "AI Recommendations",
  "description": "Get actionable AI-powered insights for your game",
  "source": "@site/docs/ai-analytics/recommendations.md",
  "sourceDirName": "ai-analytics",
  "slug": "/ai-analytics/recommendations",
  "permalink": "/docs/ai-analytics/recommendations",
  "draft": false,
  "unlisted": false,
  "editUrl": "https://github.com/game-insights/game-insights-docs/tree/main/docs/ai-analytics/recommendations.md",
  "tags": [],
  "version": "current",
  "lastUpdatedBy": "Your Name",
  "lastUpdatedAt": 1766952328000,
  "sidebarPosition": 7,
  "frontMatter": {
    "sidebar_position": 7,
    "title": "AI Recommendations",
    "description": "Get actionable AI-powered insights for your game"
  },
  "sidebar": "docs",
  "previous": {
    "title": "Anomaly Detection",
    "permalink": "/docs/ai-analytics/anomaly-detection"
  },
  "next": {
    "title": "Overview Dashboard",
    "permalink": "/docs/dashboards/overview-dashboard"
  }
}